{
  "main": {
    "id": "a1ac10483344e0e7",
    "type": "split",
    "children": [
      {
        "id": "5a6aa17ffc14cd62",
        "type": "tabs",
        "children": [
          {
            "id": "23341e849a125ece",
            "type": "leaf",
            "state": {
              "type": "markdown",
              "state": {
                "file": "TECHNICAL/SQL/Rollback.md",
                "mode": "source",
                "source": false
              }
            }
          },
          {
            "id": "6b3a33f24e4c633f",
            "type": "leaf",
            "state": {
              "type": "markdown",
              "state": {
                "file": "TECHNICAL/OBSIDIAN/Templates/Article Template.md",
                "mode": "source",
                "source": false
              }
            }
          },
          {
            "id": "5860b7d98819c728",
            "type": "leaf",
            "state": {
              "type": "markdown",
              "state": {
                "file": "TECHNICAL/OBSIDIAN/Templates/SQL template.md",
                "mode": "source",
                "source": false
              }
            }
          }
        ],
        "currentTab": 2
      }
    ],
    "direction": "vertical"
  },
  "left": {
    "id": "7ad4eb1a170a7ea3",
    "type": "split",
    "children": [
      {
        "id": "ee75249c02439a94",
        "type": "tabs",
        "children": [
          {
            "id": "aef0ec7564cd9b75",
            "type": "leaf",
            "state": {
              "type": "file-explorer",
              "state": {
                "sortOrder": "alphabetical"
              }
            }
          },
          {
            "id": "e6e61f52fe923b62",
            "type": "leaf",
            "state": {
              "type": "search",
              "state": {
                "query": "",
                "matchingCase": false,
                "explainSearch": false,
                "collapseAll": false,
                "extraContext": false,
                "sortOrder": "alphabetical"
              }
            }
          },
          {
            "id": "ccd7d8ffe550b5b0",
            "type": "leaf",
            "state": {
              "type": "starred",
              "state": {}
            }
          }
        ]
      }
    ],
    "direction": "horizontal",
    "width": 300
  },
  "right": {
    "id": "cb54298f2a66163a",
    "type": "split",
    "children": [
      {
        "id": "c3fc93496ca248ab",
        "type": "tabs",
        "children": [
          {
            "id": "2c0454608215e882",
            "type": "leaf",
            "state": {
              "type": "backlink",
              "state": {
                "file": "TECHNICAL/OBSIDIAN/Templates/SQL template.md",
                "collapseAll": false,
                "extraContext": false,
                "sortOrder": "alphabetical",
                "showSearch": false,
                "searchQuery": "",
                "backlinkCollapsed": false,
                "unlinkedCollapsed": true
              }
            }
          },
          {
            "id": "25ebd5a46b0fe1fb",
            "type": "leaf",
            "state": {
              "type": "outgoing-link",
              "state": {
                "file": "TECHNICAL/OBSIDIAN/Templates/SQL template.md",
                "linksCollapsed": false,
                "unlinkedCollapsed": true
              }
            }
          },
          {
            "id": "54c71b9e7f58b913",
            "type": "leaf",
            "state": {
              "type": "tag",
              "state": {
                "sortOrder": "frequency",
                "useHierarchy": true
              }
            }
          },
          {
            "id": "9755e39b862e2eb4",
            "type": "leaf",
            "state": {
              "type": "outline",
              "state": {
                "file": "TECHNICAL/OBSIDIAN/Templates/SQL template.md"
              }
            }
          },
          {
            "id": "e590c1197c9341bb",
            "type": "leaf",
            "state": {
              "type": "DICE_ROLLER_VIEW",
              "state": {}
            }
          },
          {
            "id": "3441bc47a64ff75d",
            "type": "leaf",
            "state": {
              "type": "advanced-tables-toolbar",
              "state": {}
            }
          }
        ],
        "currentTab": 5
      }
    ],
    "direction": "horizontal",
    "width": 300,
    "collapsed": true
  },
  "active": "5860b7d98819c728",
  "lastOpenFiles": [
    "TECHNICAL/OBSIDIAN/Templates/TTRPG_asset Template.md",
    "TECHNICAL/OBSIDIAN/Templates/SQL template.md",
    "TECHNICAL/OBSIDIAN/Templates/Article Template.md",
    "TECHNICAL/SQL/Constraints.md",
    "TECHNICAL/SQL/Rollback.md",
    "TECHNICAL/SQL/Transactional SQL.md",
    "NON_TECHNICAL_WORK/Articles Dataview.md",
    "NON_TECHNICAL_WORK/Talking for a living.md",
    "FINANCE/Finance Tables Repository.md",
    "MOVIES_BOOKS_ART/Book Dataview.md"
  ]
}